vibetuner/__init__.py
vibetuner/__main__.py
vibetuner/assets/statics/css/.placeholder
vibetuner/assets/statics/css/bundle.css
vibetuner/assets/statics/favicons/.placeholder
vibetuner/assets/statics/favicons/favicon.ico
vibetuner/assets/statics/fonts/.placeholder
vibetuner/assets/statics/img/.placeholder
vibetuner/assets/statics/js/.placeholder
vibetuner/cli/__init__.py
vibetuner/cli/db.py
vibetuner/cli/notify.py
vibetuner/cli/run.py
vibetuner/cli/scaffold.py
vibetuner/config.py
vibetuner/context.py
vibetuner/frontend/__init__.py
vibetuner/frontend/deps.py
vibetuner/frontend/email.py
vibetuner/frontend/hotreload.py
vibetuner/frontend/lifespan.py
vibetuner/frontend/middleware.py
vibetuner/frontend/oauth.py
vibetuner/frontend/proxy.py
vibetuner/frontend/routes/__init__.py
vibetuner/frontend/routes/auth.py
vibetuner/frontend/routes/debug.py
vibetuner/frontend/routes/health.py
vibetuner/frontend/routes/language.py
vibetuner/frontend/routes/meta.py
vibetuner/frontend/routes/user.py
vibetuner/frontend/routing.py
vibetuner/frontend/templates.py
vibetuner/importer.py
vibetuner/logging.py
vibetuner/models/__init__.py
vibetuner/models/blob.py
vibetuner/models/config_entry.py
vibetuner/models/email_verification.py
vibetuner/models/mixins.py
vibetuner/models/oauth.py
vibetuner/models/registry.py
vibetuner/models/types.py
vibetuner/models/user.py
vibetuner/mongo.py
vibetuner/paths.py
vibetuner/pyproject.py
vibetuner/runtime_config.py
vibetuner/services/__init__.py
vibetuner/services/blob.py
vibetuner/services/email.py
vibetuner/services/s3_storage.py
vibetuner/sqlmodel.py
vibetuner/tasks/__init__.py
vibetuner/tasks/lifespan.py
vibetuner/tasks/worker.py
vibetuner/templates/email/magic_link.html.jinja
vibetuner/templates/email/magic_link.txt.jinja
vibetuner/templates/frontend/base/favicons.html.jinja
vibetuner/templates/frontend/base/footer.html.jinja
vibetuner/templates/frontend/base/header.html.jinja
vibetuner/templates/frontend/base/opengraph.html.jinja
vibetuner-5.0.3.dist-info/WHEEL
vibetuner-5.0.3.dist-info/entry_points.txt
vibetuner-5.0.3.dist-info/METADATA
vibetuner-5.0.3.dist-info/RECORD
