Metadata-Version: 2.3
Name: vibetuner
Version: 5.0.3
Summary: Core Python framework and blessed dependencies for production-ready FastAPI + MongoDB + HTMX projects
Keywords: fastapi,mongodb,htmx,web-framework,scaffolding,oauth,background-jobs
Author: All Tuner Labs, S.L.
License: MIT
Classifier: Development Status :: 4 - Beta
Classifier: Intended Audience :: Developers
Classifier: License :: OSI Approved :: MIT License
Classifier: Programming Language :: Python :: 3
Classifier: Programming Language :: Python :: 3.11
Classifier: Programming Language :: Python :: 3.12
Classifier: Programming Language :: Python :: 3.13
Classifier: Programming Language :: Python :: 3.14
Classifier: Framework :: FastAPI
Classifier: Topic :: Internet :: WWW/HTTP :: WSGI :: Application
Classifier: Topic :: Software Development :: Libraries :: Application Frameworks
Requires-Dist: aioboto3>=15.5.0
Requires-Dist: arel>=0.4.0
Requires-Dist: asyncer>=0.0.12
Requires-Dist: authlib>=1.6.6
Requires-Dist: beanie[zstd]>=2.0.1
Requires-Dist: click>=8.3.1
Requires-Dist: copier>=9.11.3
Requires-Dist: email-validator>=2.3.0
Requires-Dist: fastapi[standard-no-fastapi-cloud-cli]>=0.128.0
Requires-Dist: granian[pname]>=2.6.1
Requires-Dist: mailjet-rest>=1.5.1
Requires-Dist: httpx[http2]>=0.28.1
Requires-Dist: itsdangerous>=2.2.0
Requires-Dist: loguru>=0.7.3
Requires-Dist: pydantic[email]>=2.12.5
Requires-Dist: pydantic-extra-types[pycountry]>=2.11.0
Requires-Dist: pydantic-settings>=2.12.0
Requires-Dist: pyyaml>=6.0.3
Requires-Dist: redis[hiredis]>=7.1.0
Requires-Dist: rich>=14.3.1
Requires-Dist: sse-starlette>=3.2.0
Requires-Dist: starlette-babel>=1.0.3
Requires-Dist: starlette-htmx>=0.1.1
Requires-Dist: streaq[web]<6.0.0
Requires-Dist: typer-slim[standard]>=0.21.1
Requires-Dist: deprecated>=1.3.1
Requires-Dist: sqlmodel>=0.0.31
Requires-Dist: gitpython>=3.1.46
Requires-Dist: babel>=2.18.0 ; extra == 'dev'
Requires-Dist: cloudflare>=4.3.1 ; extra == 'dev'
Requires-Dist: djlint>=1.36.4 ; extra == 'dev'
Requires-Dist: granian[pname,reload]>=2.6.1 ; extra == 'dev'
Requires-Dist: rumdl>=0.1.8 ; extra == 'dev'
Requires-Dist: semver>=3.0.4 ; extra == 'dev'
Requires-Dist: taplo>=0.9.3 ; extra == 'dev'
Requires-Dist: types-aioboto3[s3]>=15.5.0 ; extra == 'dev'
Requires-Dist: types-authlib>=1.6.6.20260130 ; extra == 'dev'
Requires-Dist: types-pyyaml>=6.0.12.20250915 ; extra == 'dev'
Requires-Dist: pytest>=9.0.2 ; extra == 'test'
Requires-Dist: pytest-asyncio>=1.3.0 ; extra == 'test'
Requires-Python: >=3.11
Project-URL: Homepage, https://vibetuner.alltuner.com/
Project-URL: Documentation, https://vibetuner.alltuner.com/
Project-URL: Repository, https://github.com/alltuner/vibetuner
Project-URL: Issues, https://github.com/alltuner/vibetuner/issues
Project-URL: Changelog, https://github.com/alltuner/vibetuner/blob/main/CHANGELOG.md
Provides-Extra: dev
Provides-Extra: test
